kolin/__init__.py
kolin/setup.py
kolin-0.6.dist-info/METADATA
kolin-0.6.dist-info/WHEEL
kolin-0.6.dist-info/top_level.txt
kolin-0.6.dist-info/RECORD
