Metadata-Version: 2.1
Name: kolin
Version: 0.6
Summary: Allows you to use kolin language
Home-page: https://github.com/SCORPIA-oss/Python-Shell
Author: Downey
Author-email: xsumagravity@gmail.com
License: UNKNOWN
Platform: UNKNOWN
Classifier: Programming Language :: Python :: 3
Classifier: License :: OSI Approved :: MIT License
Classifier: Operating System :: MacOS
Requires-Python: >=3.0
